aldryn_sites/__init__.py
aldryn_sites/apps.py
aldryn_sites/conf.py
aldryn_sites/middleware.py
aldryn_sites/models.py
aldryn_sites/tests.py
aldryn_sites/utils.py
aldryn_sites-0.5.8.dist-info/DESCRIPTION.rst
aldryn_sites-0.5.8.dist-info/METADATA
aldryn_sites-0.5.8.dist-info/RECORD
aldryn_sites-0.5.8.dist-info/WHEEL
aldryn_sites-0.5.8.dist-info/metadata.json
aldryn_sites-0.5.8.dist-info/top_level.txt
