Metadata-Version: 2.0
Name: aldryn-sites
Version: 0.5.8
Summary: An extension for django.contrib.sites, featuring domain redirects and automatic population of the django.contrib.sites.Site table based on settings.
Home-page: https://github.com/aldryn/aldryn-sites/
Author: Stefan Foulis
Author-email: stefan@foulis.ch
License: BSD
Platform: OS Independent
Classifier: Development Status :: 4 - Beta
Classifier: Framework :: Django
Classifier: Intended Audience :: Developers
Classifier: License :: OSI Approved :: BSD License
Classifier: Operating System :: OS Independent
Classifier: Programming Language :: Python
Classifier: Topic :: Internet :: WWW/HTTP
Classifier: Programming Language :: Python :: 2.7
Requires-Dist: Django (>=1.5)
Requires-Dist: YURL (>=0.13)
Requires-Dist: django-appconf
